LICENCE
pytest_split/__init__.py
pytest_split/algorithms.py
pytest_split/cli.py
pytest_split/ipynb_compatibility.py
pytest_split/plugin.py
pytest_split/py.typed
pytest_split_ext-0.8.1.dist-info/METADATA
pytest_split_ext-0.8.1.dist-info/WHEEL
pytest_split_ext-0.8.1.dist-info/entry_points.txt
pytest_split_ext-0.8.1.dist-info/RECORD
