Metadata-Version: 2.1
Name: pytest-split-ext
Version: 0.8.1
Summary: Pytest plugin which splits the test suite to equally sized sub suites based on test execution time.
Home-page: https://jerry-git.github.io/pytest-split
License: MIT
Keywords: pytest,plugin,split,tests
Author: Jerry Pussinen
Author-email: jerry.pussinen@gmail.com
Requires-Python: >=3.7.1,<4.0
Classifier: Development Status :: 4 - Beta
Classifier: Intended Audience :: Developers
Classifier: License :: OSI Approved :: MIT License
Classifier: Operating System :: OS Independent
Classifier: Programming Language :: Python
Classifier: Programming Language :: Python :: 3
Classifier: Programming Language :: Python :: 3.8
Classifier: Programming Language :: Python :: 3.9
Classifier: Programming Language :: Python :: 3.10
Classifier: Programming Language :: Python :: 3.11
Classifier: Programming Language :: Python :: 3.7
Classifier: Topic :: Software Development :: Libraries :: Python Modules
Classifier: Typing :: Typed
Requires-Dist: pytest (>=5,<8)
Requires-Dist: twine (>=4.0.2,<5.0.0)
Project-URL: Documentation, https://jerry-git.github.io/pytest-split
Project-URL: Repository, https://github.com/jerry-git/pytest-split
